[
{
"gen_id" : "2",
"gen_maklerId" : "2",
"gen_unique" : "tJu9wA4WOFN99ljnMU0",
"gen_title" : "360° NA PREDAJ 2 izbový byt v centre Stupavy",
"gen_firstImage" : "1",
"gen_village" : "3327",
"gen_district" : "34",
"gen_region" : "2",
"gen_price" : "92.500 €",
"gen_category" : "1",
"gen_floor" : "58 m2",
"gen_condition" : "2",
"gen_balcony" : "0",
"gen_lodge" : "1",
"gen_terrace" : "0",
"gen_parking" : "2",
"gen_street" : "Bratislavská",
"gen_type" : "2",
"gen_upstair" : "6",
"gen_note" : "Na predaj 2 izbový byt v slušnom pôvodnom stavena 6 poschodí o celkovej výmere 50 m2. Byt má murované jadro, oddelenú kúpeľňu a toaletu. V byte sa nachádzajú plastové okná a plávajúca podlaha. Možnosť prerobenia podľa vlastných predstáv. K bytu prináleží okrem latkovej pivnice na prízemí aj zatvárací balkónik o výmere cca 3 m2 na medziposchodí, ktorý užíva aj susedný jeden byt. Bytový dom má vlastnú kotoľňu, čím náklady na kúrenie sú podstatne nižšie voči podobným domom a bytom v nich. Zálohový predpis pre 1 osobu je len 92 500 € za mesiac. Bytový dom prešiel rozsiahlou rekonštrukciou a je zateplený. Byt je bez tiarch a je kúpou voľný.",
"gen_area" : "V tesnej blízkosti bytového domu sa nachádza materská škola, nákupné centrum BILLA, potraviny CBA, cukráreň ale aj miestna riečka s menom Mláka. Pri bytovom dome je možné bez problémov parkovať.",
"gen_virtualVideo" : "https://my.matterport.com/show/?m=DCFoEXwzLZm",
"gen_top" : "1",
"gen_new" : "0",
"gen_exclusiv" : "0",
"gen_discount" : "1",
"gen_reserve" : "0",
"gen_centre" : "0",
"cat_id" : "1",
"cat_note" : "Byty",
"typ_id" : "2",
"typ_note" : "Jednoizbový byt",
"vil_id" : "3327",
"vil_fullname" : "Stupava",
"vil_shortname" : "Stupava",
"vil_zip" : "900 31",
"vil_district_id" : "34",
"vil_region_id" : "2",
"dis_id" : "34",
"dis_name" : "Malacky",
"dis_veh_reg_num" : "MA",
"dis_code" : "106",
"dis_region_id" : "2",
"reg_id" : "2",
"reg_name" : "Bratislavský kraj",
"reg_shortcut" : "BL",
"par_id" : "2",
"par_note" : "Verejné parkovanie",
"con_id" : "2",
"con_note" : "Starší panelový dom",
"mak_id" : "2",
"mak_title" : "",
"mak_name" : "Rastislav",
"mak_lastName" : "Rehák",
"mak_email" : "rastislav.rehak@fermata.sk",
"mak_mobil" : "+421 904 478 738",
"images" : {
"image01" : "01_000000002.jpg",
"image02" : "02_000000002.jpg",
"image03" : "03_000000002.jpg",
"image04" : "04_000000002.jpg",
"image05" : "05_000000002.jpg",
"image06" : "06_000000002.jpg",
"image07" : "07_000000002.jpg",
"image08" : "08_000000002.jpg",
"image09" : "09_000000002.jpg",
"image10" : "10_000000002.jpg",
"image11" : "11_000000002.jpg",
"image12" : "12_000000002.jpg",
"image13" : "13_000000002.jpg",
"image14" : "14_000000002.jpg",
"image15" : "15_000000002.jpg",
"image16" : "17_000000002.jpg"
}
}
]
